{"cameraMode":{"drawMode":0,"name":"Shaded","section":"Shading Mode"},"sceneLighting":true,"audioPlay":false,"sceneViewState":{"showFog":true,"showMaterialUpdate":false,"showSkybox":true,"showFlares":true,"showImageEffects":true,"showParticleSystems":true},"in2DMode":false,"pivot":{"x":20.34821128845215,"y":8.490933418273926,"z":-22.482248306274415},"rotation":{"x":-0.12480250000953675,"y":0.841181755065918,"z":-0.21955497562885285,"w":-0.4781561493873596},"size":41.568016052246097,"orthographic":false}